hillstone_client/__init__.py
hillstone_client/hillstone.py
hillstone_client/impl_scapy.py
hillstone_client/platform_linux.py
hillstone_client-1.0.1.data/scripts/hillstone-client
hillstone_client-1.0.1.dist-info/LICENSE
hillstone_client-1.0.1.dist-info/METADATA
hillstone_client-1.0.1.dist-info/WHEEL
hillstone_client-1.0.1.dist-info/top_level.txt
hillstone_client-1.0.1.dist-info/RECORD
