Metadata-Version: 2.1
Name: hillstone-client
Version: 1.0.1
Summary: Simple Hillstone client for linux
Home-page: https://github.com/dankernel/hilldust
Author: dankernel, dsparch
Author-email: dkdkernel@gmail.com
License: UNKNOWN
Platform: UNKNOWN
Requires-Python: >=3.8
Requires-Dist: cryptography (==36.0.1)
Requires-Dist: scapy (==2.4.5)
